runecaller/__bases__.py
runecaller/__init__.py
runecaller/lifecycles.py
runecaller/runes.py
runecaller/service_locator.py
runecaller/events/__init__.py
runecaller/events/advanced.py
runecaller/events/dispatch.py
runecaller/events/enhancements.py
runecaller/events/errors.py
runecaller/events/event.py
runecaller/events/observe.py
runecaller/events/robust.py
runecaller/events/robustapply.py
runecaller/events/saferef.py
runecaller/events/schema.py
runecaller/events/subscribe.py
runecaller/hooks/__init__.py
runecaller/hooks/hook_config.py
runecaller/hooks/hook_executor.py
runecaller/hooks/hook_manager.py
runecaller/hooks/hook_register.py
runecaller/hooks/native_hooks.py
runecaller/mods/__init__.py
runecaller/mods/extensions/__init__.py
runecaller/mods/extensions/auditing.py
runecaller/mods/extensions/dependency.py
runecaller/mods/extensions/framework.py
runecaller/mods/extensions/metadata.py
runecaller/mods/extensions/policy.py
runecaller/mods/extensions/reloader.py
runecaller/mods/extensions/visualizer.py
runecaller/mods/plugins/__init__.py
runecaller/mods/plugins/loader.py
runecaller/mods/plugins/manager.py
runecaller/mods/plugins/sandbox.py
runecaller-0.1.4.dist-info/LICENSE.md
runecaller-0.1.4.dist-info/METADATA
runecaller-0.1.4.dist-info/WHEEL
runecaller-0.1.4.dist-info/top_level.txt
runecaller-0.1.4.dist-info/RECORD
