Metadata-Version: 2.2
Name: runecaller
Version: 0.1.4
Summary: Flexible framework for event management, hooks, and dynamic plugin systems
Author-email: DirtyWork Solutions Limited <runecaller@open.dirtywork.solutions>, Aidan Hogg <ahogg@dirtywork.solutions>
Maintainer-email: DirtyWork Solutions Limited <runecaller@open.dirtywork.solutions>
License: # MIT License
Project-URL: Homepage, https://open.dirtywork.solutions/runecaller
Project-URL: Documentation, https://github.com/DirtyWork-Solutions/RuneCaller/docs/INDEX.md
Project-URL: Source, https://github.com/DirtyWork-Solutions/RuneCaller
Project-URL: Issues, https://github.com/DirtyWork-Solutions/RuneCaller/tree/main/.github/ISSUE_TEMPLATE
Keywords: dispatcher,dispatch,pydispatch,event,signal,sender,receiver,propagate,multi-consumer,multi-producer,saferef,robustapply,apply
Classifier: Programming Language :: Python :: 3
Classifier: Programming Language :: Python :: 3.13
Classifier: Programming Language :: Python :: Implementation :: CPython
Classifier: License :: OSI Approved :: MIT License
Classifier: Operating System :: OS Independent
Classifier: Development Status :: 2 - Pre-Alpha
Classifier: Environment :: Console
Classifier: Intended Audience :: Developers
Classifier: Topic :: System
Classifier: Topic :: Software Development :: Libraries :: Python Modules
Classifier: Topic :: Utilities
Requires-Python: >=3.13
License-File: LICENSE.md
Requires-Dist: setuptools~=75.8.2
Requires-Dist: pyforged~=0.2.2
Requires-Dist: bedrocked~=0.1.3
Provides-Extra: dev
Requires-Dist: tox; extra == "dev"
Requires-Dist: pytest; extra == "dev"
Requires-Dist: pytest-cov; extra == "dev"
